LandsatL2C2/EEAPI.py
LandsatL2C2/LandsatL2C2.py
LandsatL2C2/M2M_credentials.py
LandsatL2C2/UTM.py
LandsatL2C2/WRS2Descending.py
LandsatL2C2/WRS2_descending_polygons.geojson
LandsatL2C2/__init__.py
LandsatL2C2/backends.py
LandsatL2C2/credentials.py
LandsatL2C2/transform.py
LandsatL2C2/version.py
landsatl2c2-2.0.0.dist-info/licenses/LICENSE
landsatl2c2-2.0.0.dist-info/METADATA
landsatl2c2-2.0.0.dist-info/WHEEL
landsatl2c2-2.0.0.dist-info/entry_points.txt
landsatl2c2-2.0.0.dist-info/top_level.txt
landsatl2c2-2.0.0.dist-info/RECORD
