Metadata-Version: 2.4
Name: LandsatL2C2
Version: 2.0.0
Summary: Landsat Level 2 Collection 2 Search & Download Utility
Author-email: "Gregory H. Halverson" <gregory.h.halverson@jpl.nasa.gov>
Project-URL: Homepage, https://github.com/JPL-Evapotranspiration-Algorithms/LandsatL2C2
Classifier: Programming Language :: Python :: 3
Classifier: Operating System :: OS Independent
Requires-Python: >=3.10
License-File: LICENSE
Requires-Dist: boto3
Requires-Dist: colored-logging
Requires-Dist: geopandas
Requires-Dist: matplotlib
Requires-Dist: pandas
Requires-Dist: planetary-computer
Requires-Dist: pyproj
Requires-Dist: pystac-client
Requires-Dist: python-dateutil
Requires-Dist: rasterio
Requires-Dist: rasters
Requires-Dist: requests
Requires-Dist: shapely
Provides-Extra: dev
Requires-Dist: build; extra == "dev"
Requires-Dist: pytest>=6.0; extra == "dev"
Requires-Dist: pytest-cov; extra == "dev"
Requires-Dist: jupyter; extra == "dev"
Requires-Dist: pytest; extra == "dev"
Requires-Dist: twine; extra == "dev"
Dynamic: license-file
